firestore_size/__init__.py
firestore_size/calculate.py
firestore_size-1.0.1.dist-info/LICENSE
firestore_size-1.0.1.dist-info/METADATA
firestore_size-1.0.1.dist-info/WHEEL
firestore_size-1.0.1.dist-info/top_level.txt
firestore_size-1.0.1.dist-info/RECORD
