Metadata-Version: 2.1
Name: firestore-size
Version: 1.0.1
Summary: Python library to calculate the approximate size of a firestore document
Home-page: https://github.com/WaseemSabir/firestore_size
Author: Waseem Sabir
Author-email: waseemsabir99@gmail.com
License: MIT
Platform: UNKNOWN
Classifier: Programming Language :: Python :: 3
Classifier: License :: OSI Approved :: MIT License
Classifier: Operating System :: OS Independent
License-File: LICENSE
